tabcompleter.py
tabcompleter-1.3.3.dist-info/LICENSE
tabcompleter-1.3.3.dist-info/METADATA
tabcompleter-1.3.3.dist-info/WHEEL
tabcompleter-1.3.3.dist-info/top_level.txt
tabcompleter-1.3.3.dist-info/RECORD
